toxigen/__init__.py
toxigen/alice.py
toxigen/language_models.py
toxigen/pretrained_classifiers.py
toxigen/utils.py
toxigen-1.1.0.dist-info/METADATA
toxigen-1.1.0.dist-info/WHEEL
toxigen-1.1.0.dist-info/top_level.txt
toxigen-1.1.0.dist-info/RECORD
