Metadata-Version: 2.1
Name: toxigen
Version: 1.1.0
Summary: Code support for ToxiGen
Home-page: https://github.com/microsoft/toxigen
Author: Thomas Hartvigsen
Author-email: tomh@mit.edu
License: BSD 2-clause
Platform: UNKNOWN
Classifier: Intended Audience :: Science/Research
Classifier: License :: OSI Approved :: BSD License
Classifier: Programming Language :: Python :: 3.8
Requires-Dist: torch
Requires-Dist: numpy
Requires-Dist: transformers (==4.16.2)
Requires-Dist: pandas
